Metadata-Version: 2.1
Name: thucyd
Version: 0.2.3
Summary: Reference library for advanced eigenanalysis.
Home-page: https://gitlab.com/thucyd-dev/thucyd
Author: Jay Damask
Author-email: jaydamask@buell-lane-press.co
License: Apache License 2.0
Project-URL: Documentation, https://gitlab.com/thucyd-dev/thucyd/
Project-URL: Changelog, https://gitlab.com/thucyd-dev/thucyd/
Project-URL: Issue Tracker, https://gitlab.com/thucyd-dev/thucyd/issues
Keywords: eigenanalysis
Classifier: Development Status :: 4 - Beta
Classifier: Environment :: Console
Classifier: Intended Audience :: Science/Research
Classifier: License :: OSI Approved :: Apache Software License
Classifier: Operating System :: OS Independent
Classifier: Programming Language :: Python :: 3.7
Classifier: Programming Language :: Python :: 3.8
Classifier: Programming Language :: Python :: 3.9
Classifier: Programming Language :: Python :: 3.10
Classifier: Programming Language :: Python :: 3.11
Classifier: Programming Language :: Python :: 3.12
Classifier: Topic :: Scientific/Engineering
Requires-Python: >=3.7
License-File: LICENSE
Requires-Dist: numpy>=1.23
